fmp/__init__.py
fmp/config.py
fmp/fundamental.py
fmp/market.py
fmp/news.py
fmp/quote.py
FinancialModelingPrep_Python-0.0.5.dist-info/LICENSE
FinancialModelingPrep_Python-0.0.5.dist-info/METADATA
FinancialModelingPrep_Python-0.0.5.dist-info/WHEEL
FinancialModelingPrep_Python-0.0.5.dist-info/top_level.txt
FinancialModelingPrep_Python-0.0.5.dist-info/RECORD
