Metadata-Version: 2.1
Name: FinancialModelingPrep-Python
Version: 0.0.5
Summary: Financial Modeling Prep API Python Implementation
Home-page: https://github.com/thinh-vu/FinancialModelingPrep
Author: Thinh Vu
Author-email: support@thinhvu.com
Classifier: Programming Language :: Python :: 3
Classifier: License :: OSI Approved :: MIT License
Classifier: Operating System :: OS Independent
Requires-Python: >=3.7
License-File: LICENSE
